project_platter/__init__.py
project_platter/cli.py
project_platter-1.0.0.dist-info/licenses/LICENSE
project_platter-1.0.0.dist-info/METADATA
project_platter-1.0.0.dist-info/WHEEL
project_platter-1.0.0.dist-info/entry_points.txt
project_platter-1.0.0.dist-info/top_level.txt
project_platter-1.0.0.dist-info/RECORD
