Metadata-Version: 2.4
Name: project-platter
Version: 1.0.0
Summary: A CLI tool to serve up ready-to-go AI/automation project templates with Git and GitHub setup.
Author-email: Hamza Ghaffar <hamza.ghaffar.edu@gmail.com>
License: MIT
Keywords: automation,genai,cli,project-bootstrap,platter
Classifier: Programming Language :: Python :: 3
Classifier: License :: OSI Approved :: MIT License
Classifier: Operating System :: OS Independent
Requires-Python: >=3.8
License-File: LICENSE
Requires-Dist: requests>=2.25.0
Dynamic: license-file
